petal_flight_log-0.2.5.dist-info/METADATA
petal_flight_log-0.2.5.dist-info/WHEEL
petal_flight_log-0.2.5.dist-info/entry_points.txt
petal_flight_log-0.2.5.dist-info/licenses/LICENSE.md
petal_flight_log/__init__.py
petal_flight_log/data_model.py
petal_flight_log/job_manager.py
petal_flight_log/jobs.py
petal_flight_log/plugin.py
petal_flight_log-0.2.5.dist-info/RECORD
