Metadata-Version: 2.1
Name: petal-flight-log
Version: 0.2.5
Summary: A petal for creating flight logs and download Ulog files from PXHawk
Author-Email: khbalhandawi <khalil.alhandawi@mail.mcgill.ca>
License: LICENSE.md
Requires-Python: >=3.10
Requires-Dist: petal-app-manager>=0.1.1
